LICENCE
README.md
setup.py
selforge/__init__.py
selforge/sel300.py
selforge/sel700.py
selforge.egg-info/PKG-INFO
selforge.egg-info/SOURCES.txt
selforge.egg-info/dependency_links.txt
selforge.egg-info/top_level.txt