Metadata-Version: 2.1
Name: selforge
Version: 0.3.1
Author: Elisandro Peixoto
Author-email: elisandropeixoto21@gmail.com
Requires-Python: <3.13
License-File: LICENCE
